condamagic.py
condamagic-0.2.1.dist-info/DESCRIPTION.rst
condamagic-0.2.1.dist-info/METADATA
condamagic-0.2.1.dist-info/RECORD
condamagic-0.2.1.dist-info/WHEEL
condamagic-0.2.1.dist-info/metadata.json
condamagic-0.2.1.dist-info/top_level.txt
