Metadata-Version: 2.0
Name: condamagic
Version: 0.2.1
Summary: %condamagic for IPython
Home-page: https://github.com/minrk/condamagic
Author: Min RK
Author-email: benjaminrk@gmail.com
License: BSD
Keywords: Interactive,Interpreter,Shell
Platform: Linux
Platform: Mac OS X
Classifier: Intended Audience :: Developers
Classifier: Intended Audience :: System Administrators
Classifier: License :: OSI Approved :: BSD License
Classifier: Programming Language :: Python
Classifier: Programming Language :: Python :: 2
Classifier: Programming Language :: Python :: 3
